niq/__init__.py
niq/_niq.py
niq-1.2.2.dist-info/LICENSE
niq-1.2.2.dist-info/METADATA
niq-1.2.2.dist-info/WHEEL
niq-1.2.2.dist-info/top_level.txt
niq-1.2.2.dist-info/RECORD
