Metadata-Version: 2.1
Name: niq
Version: 1.2.2
Summary: Nick's library of extraneous utils
Home-page: https://github.com/kimegitee/niq
Author: kimegitee
Author-email: kimegitee@gmail.com
License: MIT
Platform: UNKNOWN
Requires-Dist: xxhash (<2,>=1.4.0)
Requires-Dist: joblib (<0.15,>=0.14.0)
